README.md
setup.py
ortools-stubs/__init__.pyi
ortools-stubs/algorithms/__init__.pyi
ortools-stubs/constraint_solver/__init__.pyi
ortools-stubs/constraint_solver/assignment_pb2.pyi
ortools-stubs/constraint_solver/routing_enums_pb2.pyi
ortools-stubs/constraint_solver/routing_parameters_pb2.pyi
ortools-stubs/constraint_solver/search_limit_pb2.pyi
ortools-stubs/constraint_solver/solver_parameters_pb2.pyi
ortools-stubs/data/__init__.pyi
ortools-stubs/data/rcpsp_pb2.pyi
ortools-stubs/graph/__init__.pyi
ortools-stubs/linear_solver/__init__.pyi
ortools-stubs/linear_solver/linear_solver_pb2.pyi
ortools-stubs/sat/__init__.pyi
ortools-stubs/sat/cp_model_pb2.pyi
ortools-stubs/sat/sat_parameters_pb2.pyi
ortools-stubs/sat/python/__init__.pyi
ortools-stubs/util/__init__.pyi
ortools-stubs/util/optional_boolean_pb2.pyi
ortools_stubs.egg-info/PKG-INFO
ortools_stubs.egg-info/SOURCES.txt
ortools_stubs.egg-info/dependency_links.txt
ortools_stubs.egg-info/top_level.txt