Metadata-Version: 2.1
Name: ortools-stubs
Version: 7.7.0
Summary: PEP 561 type stubs for Google OR-Tools
Home-page: https://github.com/stradivari96/ortools-stubs
Maintainer: Xiang Chen
Maintainer-email: xiangchenchen96@gmail.com
License: MIT
Platform: UNKNOWN
